log2json/__init__.py
log2json/__main__.py
log2json/core.py
log2json/status.py
log2json/cli/__init__.py
log2json/cli/definition.py
log2json_fauzanelka-0.0.4.dist-info/LICENSE
log2json_fauzanelka-0.0.4.dist-info/METADATA
log2json_fauzanelka-0.0.4.dist-info/WHEEL
log2json_fauzanelka-0.0.4.dist-info/entry_points.txt
log2json_fauzanelka-0.0.4.dist-info/top_level.txt
log2json_fauzanelka-0.0.4.dist-info/RECORD
