Metadata-Version: 2.1
Name: log2json-fauzanelka
Version: 0.0.4
Summary: Convert log to json
Home-page: https://github.com/fauzanelka/log2json
Author: Fauzan Elka
Author-email: fauzan.elka@gmail.com
License: UNKNOWN
Project-URL: Bug Tracker, https://github.com/fauzanelka/log2json/issues
Platform: UNKNOWN
Classifier: Programming Language :: Python :: 3
Classifier: License :: OSI Approved :: MIT License
Classifier: Operating System :: OS Independent
Requires-Python: >=3.6
